video_composer/__init__.py
video_composer/batch_processor.py
video_composer/cli.py
video_composer/composer.py
video_composer/config.py
video_composer/models.py
video_composer/py.typed
video_composer/services/__init__.py
video_composer/services/common_stock.py
video_composer/services/openai_service.py
video_composer/services/pexels_service.py
video_composer/services/pixabay_service.py
video_composer/services/stock_provider.py
video_composer/utils/__init__.py
video_composer/utils/subtitles.py
video_composer/utils/video_processor.py
video_composer/yaml_config/__init__.py
video_composer/yaml_config/video_config.py
video_composer-0.4.0.dist-info/METADATA
video_composer-0.4.0.dist-info/WHEEL
video_composer-0.4.0.dist-info/entry_points.txt
video_composer-0.4.0.dist-info/licenses/LICENSE
video_composer-0.4.0.dist-info/RECORD
