Metadata-Version: 2.4
Name: video-composer
Version: 0.4.0
Summary: AI-powered social video automation tool for generating vertical short-form marketing videos with TTS, subtitles, and stock footage
Project-URL: Homepage, https://github.com/youhanasheriff/video-composer
Project-URL: Documentation, https://github.com/youhanasheriff/video-composer#readme
Project-URL: Repository, https://github.com/youhanasheriff/video-composer.git
Project-URL: Issues, https://github.com/youhanasheriff/video-composer/issues
Project-URL: Changelog, https://github.com/youhanasheriff/video-composer/blob/main/CHANGELOG.md
Author-email: Youhana Sheriff <youhana@sheriax.com>
Maintainer-email: Youhana Sheriff <youhana@sheriax.com>
License: MIT
License-File: LICENSE
Keywords: ai,automation,content-creation,marketing,openai,pexels,reels,short-form,shorts,social-media,subtitles,text-to-speech,tiktok,tts,vertical-video,video,whisper
Classifier: Development Status :: 4 - Beta
Classifier: Environment :: Console
Classifier: Intended Audience :: Developers
Classifier: Intended Audience :: End Users/Desktop
Classifier: Intended Audience :: Information Technology
Classifier: License :: OSI Approved :: MIT License
Classifier: Operating System :: OS Independent
Classifier: Programming Language :: Python :: 3
Classifier: Programming Language :: Python :: 3.11
Classifier: Programming Language :: Python :: 3.12
Classifier: Programming Language :: Python :: 3.13
Classifier: Topic :: Multimedia :: Sound/Audio :: Speech
Classifier: Topic :: Multimedia :: Video
Classifier: Topic :: Multimedia :: Video :: Conversion
Classifier: Topic :: Scientific/Engineering :: Artificial Intelligence
Classifier: Typing :: Typed
Requires-Python: >=3.11
Requires-Dist: aiofiles>=23.2.1
Requires-Dist: httpx>=0.27.0
Requires-Dist: moviepy>=2.0.0
Requires-Dist: numpy>=1.26.0
Requires-Dist: openai>=1.12.0
Requires-Dist: pillow>=10.2.0
Requires-Dist: pydantic-settings>=2.2.0
Requires-Dist: pydantic>=2.6.0
Requires-Dist: python-dotenv>=1.0.1
Requires-Dist: pyyaml>=6.0.0
Requires-Dist: rich>=13.7.0
Requires-Dist: tenacity>=8.2.3
Requires-Dist: typer>=0.9.0
Provides-Extra: dev
Requires-Dist: build>=1.0.0; extra == 'dev'
Requires-Dist: mypy>=1.8.0; extra == 'dev'
Requires-Dist: pre-commit>=3.6.0; extra == 'dev'
Requires-Dist: pytest-asyncio>=0.23.0; extra == 'dev'
Requires-Dist: pytest-cov>=4.1.0; extra == 'dev'
Requires-Dist: pytest>=8.0.0; extra == 'dev'
Requires-Dist: ruff>=0.2.0; extra == 'dev'
Requires-Dist: twine>=5.0.0; extra == 'dev'
Requires-Dist: types-aiofiles>=23.2.0; extra == 'dev'
Requires-Dist: types-pyyaml>=6.0.0; extra == 'dev'
